coopertunes/__init__.py
coopertunes/distributed.py
coopertunes/logger.py
coopertunes/utils.py
coopertunes/checkpoints/melgan_pretrained.pt
coopertunes/checkpoints/performancernn_pretrained.pt
coopertunes/datasets/AudioDataset.py
coopertunes/datasets/GANSynthDataset.py
coopertunes/datasets/MelDataset.py
coopertunes/datasets/MidiDataset.py
coopertunes/datasets/__init__.py
coopertunes/datatools/__init__.py
coopertunes/datatools/config.py
coopertunes/datatools/downloaders.py
coopertunes/datatools/miditools.py
coopertunes/datatools/process.py
coopertunes/hparams/Audio2Mel.py
coopertunes/hparams/GANSynth.py
coopertunes/hparams/MelGan.py
coopertunes/hparams/MelSpecVAE.py
coopertunes/hparams/MelSpecVQVAE.py
coopertunes/hparams/PerformanceRNN.py
coopertunes/hparams/__init__.py
coopertunes/hparams/hparams.py
coopertunes/models/Audio2Mel.py
coopertunes/models/GANSynth.py
coopertunes/models/MelGan.py
coopertunes/models/MelSpecVAE.py
coopertunes/models/MelSpecVQVAE.py
coopertunes/models/PerformanceRNN.py
coopertunes/models/PerformanceRNNattentive.py
coopertunes/models/__init__.py
coopertunes/models/model.py
coopertunes/supervisors/Audio2Mel.py
coopertunes/supervisors/GANSynth.py
coopertunes/supervisors/MelGan.py
coopertunes/supervisors/MelSpecVAE.py
coopertunes/supervisors/MelSpecVQVAE.py
coopertunes/supervisors/PerformanceRNN.py
coopertunes/supervisors/__init__.py
coopertunes-0.2.0.dist-info/LICENSE
coopertunes-0.2.0.dist-info/METADATA
coopertunes-0.2.0.dist-info/WHEEL
coopertunes-0.2.0.dist-info/top_level.txt
coopertunes-0.2.0.dist-info/RECORD
