Metadata-Version: 2.1
Name: coopertunes
Version: 0.2.0
Summary: Hub for music machine learning  generating audio
Author-email: Łukasz Bondaruk <lukas.bond07@gmail.com>, Oskar Bartosz <oskbsz@gmail.com>, Andrzej Kusiak <andrzej.kusiak00@gmail.com>
Project-URL: Homepage, https://github.com/Szakulli07/coopertunes
Requires-Python: >=3.10
License-File: LICENSE
Requires-Dist: coloredlogs >=15.0.1
Requires-Dist: deepspeed ==0.12.5
Requires-Dist: einops ==0.7.0
Requires-Dist: pycodestyle ==2.10.0
Requires-Dist: pylint ==2.16.2
Requires-Dist: tensorboard ==2.15.1
Requires-Dist: mypy ==1.5.0
Requires-Dist: matplotlib ==3.8.2
Requires-Dist: numpy ==1.23.5
Requires-Dist: librosa ==0.9.1
Requires-Dist: scipy ==1.11.4
Requires-Dist: argparse ==1.4.0
Requires-Dist: torch-summary ==1.4.5
Requires-Dist: pretty-midi ==0.2.10
Requires-Dist: progress ==1.6
Requires-Dist: black ==23.12.1
Requires-Dist: torch ==2.0.1
Requires-Dist: torchaudio ==2.0.2
Requires-Dist: requests ==2.31.0
Requires-Dist: types-requests ==2.31.0.20240106
Requires-Dist: beautifulsoup4 ==4.12.2
